outside/__init__.py
outside/__main__.py
outside/code_description.py
outside/protocol_http.py
outside/protocol_websocket.py
outside/utility.py
outside_framework-1.5.8.dist-info/LICENSE
outside_framework-1.5.8.dist-info/METADATA
outside_framework-1.5.8.dist-info/WHEEL
outside_framework-1.5.8.dist-info/top_level.txt
outside_framework-1.5.8.dist-info/RECORD
