Metadata-Version: 2.2
Name: outside-framework
Version: 1.5.8
Summary: An easy-to-use python web framework. Inspired by Flask.
Author-email: toni08bit <hello1502.channel@gmail.com>
Project-URL: Homepage, https://github.com/toni08bit/outside
Project-URL: Issues, https://github.com/toni08bit/outside/issues
Classifier: Programming Language :: Python :: 3
Classifier: License :: OSI Approved :: MIT License
Classifier: Operating System :: OS Independent
Requires-Python: >=3.8
License-File: LICENSE
